itk/_ITKIOBioRadPython.pyd
itk/_ITKIOBrukerPython.pyd
itk/_ITKIOGEPython.pyd
itk/_ITKIOHDF5Python.pyd
itk/_ITKIOIPLPython.pyd
itk/_ITKIOJPEG2000Python.pyd
itk/_ITKIOLSMPython.pyd
itk/_ITKIOMINCPython.pyd
itk/_ITKIOMRCPython.pyd
itk/_ITKIORAWPython.pyd
itk/_ITKIOSiemensPython.pyd
itk/_ITKIOSpatialObjectsPython.pyd
itk/_ITKIOStimulatePython.pyd
itk/_ITKIOTransformBasePython.pyd
itk/_ITKIOTransformHDF5Python.pyd
itk/_ITKIOTransformInsightLegacyPython.pyd
itk/_ITKIOTransformMatlabPython.pyd
itk/Configuration/ITKIOBioRad_snake_case.py
itk/Configuration/ITKIOBioRadConfig.py
itk/Configuration/ITKIOBruker_snake_case.py
itk/Configuration/ITKIOBrukerConfig.py
itk/Configuration/ITKIOGE_snake_case.py
itk/Configuration/ITKIOGEConfig.py
itk/Configuration/ITKIOHDF5_snake_case.py
itk/Configuration/ITKIOHDF5Config.py
itk/Configuration/ITKIOIPL_snake_case.py
itk/Configuration/ITKIOIPLConfig.py
itk/Configuration/ITKIOJPEG2000_snake_case.py
itk/Configuration/ITKIOJPEG2000Config.py
itk/Configuration/ITKIOLSM_snake_case.py
itk/Configuration/ITKIOLSMConfig.py
itk/Configuration/ITKIOMINC_snake_case.py
itk/Configuration/ITKIOMINCConfig.py
itk/Configuration/ITKIOMRC_snake_case.py
itk/Configuration/ITKIOMRCConfig.py
itk/Configuration/ITKIORAW_snake_case.py
itk/Configuration/ITKIORAWConfig.py
itk/Configuration/ITKIOSiemens_snake_case.py
itk/Configuration/ITKIOSiemensConfig.py
itk/Configuration/ITKIOSpatialObjects_snake_case.py
itk/Configuration/ITKIOSpatialObjectsConfig.py
itk/Configuration/ITKIOStimulate_snake_case.py
itk/Configuration/ITKIOStimulateConfig.py
itk/Configuration/ITKIOTransformBase_snake_case.py
itk/Configuration/ITKIOTransformBaseConfig.py
itk/Configuration/ITKIOTransformHDF5_snake_case.py
itk/Configuration/ITKIOTransformHDF5Config.py
itk/Configuration/ITKIOTransformInsightLegacy_snake_case.py
itk/Configuration/ITKIOTransformInsightLegacyConfig.py
itk/Configuration/ITKIOTransformMatlab_snake_case.py
itk/Configuration/ITKIOTransformMatlabConfig.py
itk/itkBioRadImageIOPython.py
itk_io-5.4.4.post1.dist-info/METADATA
itk_io-5.4.4.post1.dist-info/WHEEL
itk_io-5.4.4.post1.dist-info/licenses/LICENSE
itk_io-5.4.4.post1.dist-info/licenses/ITK-source/ITK/LICENSE
itk_io-5.4.4.post1.dist-info/licenses/ITK-source/ITK/NOTICE
itk_io-5.4.4.post1.dist-info/RECORD
