Metadata-Version: 2.1
Name: itk-io
Version: 5.4.4.post1
Summary: ITK is an open-source toolkit for multidimensional image analysis
Keywords: ITK,InsightToolkit,scientific,medical,image,imaging
Author-Email: Insight Software Consortium <community@itk.org>
License:                                  Apache License
Classifier: Development Status :: 4 - Beta
Classifier: Intended Audience :: Developers
Classifier: Intended Audience :: Education
Classifier: Intended Audience :: Healthcare Industry
Classifier: Intended Audience :: Science/Research
Classifier: License :: OSI Approved :: Apache Software License
Classifier: Operating System :: Android
Classifier: Operating System :: MacOS
Classifier: Operating System :: Microsoft :: Windows
Classifier: Operating System :: POSIX
Classifier: Operating System :: Unix
Classifier: Programming Language :: C++
Classifier: Programming Language :: Python
Classifier: Programming Language :: Python :: 3
Classifier: Topic :: Scientific/Engineering
Classifier: Topic :: Scientific/Engineering :: Information Analysis
Classifier: Topic :: Scientific/Engineering :: Medical Science Apps.
Classifier: Topic :: Software Development :: Libraries
Project-URL: Download, https://github.com/InsightSoftwareConsortium/ITK/releases
Project-URL: Home, https://docs.itk.org/
Project-URL: Issues, https://github.com/InsightSoftwareConsortium/ITK/issues
Project-URL: Source, https://github.com/InsightSoftwareConsortium/ITK
Requires-Python: >=3.8
Requires-Dist: itk-core==5.4.4.post1
